rai/__init__.py
rai/rai.py
rai/modules/__init__.py
rai/modules/agentbuilder/__init__.py
rai/modules/agentbuilder/agentbuilder.py
rai/modules/agentcli/__init__.py
rai/modules/agentcli/agentcli.py
rai/modules/banner/__init__.py
rai/modules/banner/banner.py
rai/modules/cli/__init__.py
rai/modules/cli/cli.py
rai/modules/config/__init__.py
rai/modules/config/config.py
rai/modules/gitutils/__init__.py
rai/modules/gitutils/gitutils.py
rai/modules/gui/__init__.py
rai/modules/gui/gui.py
rai/modules/gui/agent/__init__.py
rai/modules/gui/agent/agent.py
rai/modules/gui/button/__init__.py
rai/modules/gui/button/button.py
rai/modules/gui/colorutils/__init__.py
rai/modules/gui/colorutils/colorutils.py
rai/modules/gui/guiutils/__init__.py
rai/modules/gui/guiutils/guiutils.py
rai/modules/gui/memory/__init__.py
rai/modules/gui/memory/memory.py
rai/modules/gui/providers/__init__.py
rai/modules/gui/providers/providers.py
rai/modules/gui/team/__init__.py
rai/modules/gui/team/team.py
rai/modules/gui/tools/tools.py
rai/modules/help/__init__.py
rai/modules/help/help.py
rai/modules/logger/__init__.py
rai/modules/logger/logger.py
rai/modules/modelconfig/__init__.py
rai/modules/modelconfig/modelconfig.py
rai/modules/teamconfig/__init__.py
rai/modules/teamconfig/teamconfig.py
rai/modules/toolconfig/__init__.py
rai/modules/toolconfig/toolconfig.py
rai/modules/version/__init__.py
rai/modules/version/version.py
revolt_rai-1.0.1.dist-info/METADATA
revolt_rai-1.0.1.dist-info/WHEEL
revolt_rai-1.0.1.dist-info/entry_points.txt
revolt_rai-1.0.1.dist-info/licenses/LICENSE
revolt_rai-1.0.1.dist-info/RECORD
