Metadata-Version: 2.4
Name: revolt-rai
Version: 1.0.1
Summary: RAI is a next-gen CLI framework to automate the creation of intelligent agents and teams for cybersecurity and offensive security operations
Project-URL: Homepage, https://github.com/RevoltSecurities/RAI
Project-URL: Documentation, https://github.com/RevoltSecurities/RAI/wiki
Project-URL: Repository, https://github.com/RevoltSecurities/RAI
Project-URL: Issues, https://github.com/RevoltSecurities/RAI/issues
Author-email: "D. Sanjai Kumar" <bughunterz0047@gmail.com>, "Gokul.V" <th3gokul@gmail.com>
Maintainer-email: "D. Sanjai Kumar" <bughunterz0047@gmail.com>, "Gokul.V" <th3gokul@gmail.com>
License: MIT
License-File: LICENSE
Keywords: AI Security,AI shell,LLM Team,agno,ai-agents,ctf,ethical hacking,framework,llm,multi-agent,penetration testing,rai
Classifier: Development Status :: 5 - Production/Stable
Classifier: Environment :: Console
Classifier: Intended Audience :: Developers
Classifier: Intended Audience :: Information Technology
Classifier: License :: OSI Approved :: MIT License
Classifier: Programming Language :: Python :: 3.13
Classifier: Topic :: Security
Classifier: Topic :: Software Development :: Libraries
Classifier: Topic :: Utilities
Requires-Python: >=3.13
Requires-Dist: agno>=1.4.3
Requires-Dist: aiofiles>=24.1.0
Requires-Dist: aiohttp>=3.11.18
Requires-Dist: anthropic>=0.50.0
Requires-Dist: anyio>=4.9.0
Requires-Dist: appdirs>=1.4.4
Requires-Dist: art>=6.5
Requires-Dist: asyncio>=3.4.3
Requires-Dist: azure-ai-inference>=1.0.0b9
Requires-Dist: boto3>=1.38.6
Requires-Dist: cerebras-cloud-sdk>=1.35.0
Requires-Dist: cohere>=5.15.0
Requires-Dist: colorama>=0.4.6
Requires-Dist: customtkinter>=5.2.2
Requires-Dist: google-genai>=1.13.0
Requires-Dist: groq>=0.23.1
Requires-Dist: httpx>=0.28.1
Requires-Dist: ibm-watsonx-ai>=1.3.13
Requires-Dist: litellm>=1.67.5
Requires-Dist: llama-api-client>=0.1.1
Requires-Dist: mcp>=1.6.0
Requires-Dist: mistralai>=1.7.0
Requires-Dist: nest-asyncio>=1.6.0
Requires-Dist: ollama>=0.4.8
Requires-Dist: openai>=1.76.2
Requires-Dist: pillow>=11.2.1
Requires-Dist: prompt-toolkit>=3.0.51
Requires-Dist: pyyaml>=6.0.2
Requires-Dist: requests>=2.32.3
Requires-Dist: sqlalchemy>=2.0.41
Requires-Dist: tk>=0.1.0
